xbox_sdk/__init__.py
xbox_sdk/gamer.py
xbox_sdk/py.typed
xbox_sdk/scraper.py
xbox_sdk/user.py
xbox_sdk/lib/__init__.py
xbox_sdk/lib/client.py
xbox_sdk/lib/errors.py
xbox_sdk/lib/timer.py
xbox_sdk/xapi/__init__.py
xbox_sdk/xapi/acheivements.py
xbox_sdk/xapi/clubs.py
xbox_sdk/xapi/content.py
xbox_sdk/xapi/marketplace.py
xbox_sdk/xapi/profile.py
xbox_sdk/xapi/profile_specific.py
xbox_sdk/xapi/social.py
xbox_sdk/xapi/stats.py
xbox_sdk/xapi/xapi.py
xbox_sdk-0.0.12.dist-info/LICENSE
xbox_sdk-0.0.12.dist-info/METADATA
xbox_sdk-0.0.12.dist-info/WHEEL
xbox_sdk-0.0.12.dist-info/top_level.txt
xbox_sdk-0.0.12.dist-info/RECORD
