Metadata-Version: 2.1
Name: xbox-sdk
Version: 0.0.12
Summary: This application accesses the Xbox Live system.
Home-page: https://github.com/mjlomeli/Xbox_SDK
Author: Mauricio
Author-email: dev.mauricio.lomeli@gmail.com
Project-URL: Bug Tracker, https://github.com/mjlomeli/Xbox_SDK/issues
Platform: win32
Classifier: Programming Language :: Python :: 3.9
Classifier: Programming Language :: Python :: 3.10
Classifier: License :: OSI Approved :: MIT License
Classifier: Operating System :: OS Independent
Requires-Python: >=3.9
License-File: LICENSE
Requires-Dist: wheel
Requires-Dist: requests (>=2.28.1)
Provides-Extra: testing
Requires-Dist: pytest (>=6.0) ; extra == 'testing'
Requires-Dist: pytest-cov (>=2.0) ; extra == 'testing'
Requires-Dist: mypy (>=0.971) ; extra == 'testing'
Requires-Dist: flake8 (>=3.9) ; extra == 'testing'
Requires-Dist: tox (>=3.24) ; extra == 'testing'
